moat/lib/pid/__init__.py
moat/lib/pid/_impl.py
moat_lib_pid-0.6.7.dist-info/licenses/LICENSE
moat_lib_pid-0.6.7.dist-info/licenses/LICENSE.txt
moat_lib_pid-0.6.7.dist-info/METADATA
moat_lib_pid-0.6.7.dist-info/WHEEL
moat_lib_pid-0.6.7.dist-info/top_level.txt
moat_lib_pid-0.6.7.dist-info/RECORD
